README.rst
setup.py
mfa/__init__.py
mfa/cli.py
mfa.egg-info/PKG-INFO
mfa.egg-info/SOURCES.txt
mfa.egg-info/dependency_links.txt
mfa.egg-info/entry_points.txt
mfa.egg-info/pbr.json
mfa.egg-info/requires.txt
mfa.egg-info/top_level.txt