Metadata-Version: 1.1
Name: mfa
Version: 0.1.1
Summary: Multi-factor authentication on your command line
Home-page: https://github.com/limeburst/mfa
Author: Jihyeok Seo
Author-email: me@limeburst.net
License: UNKNOWN
Platform: UNKNOWN
Classifier: Development Status :: 3 - Alpha
Classifier: Environment :: Console
Classifier: Operating System :: POSIX
Classifier: Programming Language :: Python :: 3.4
Classifier: Topic :: Utilities
